GQCC/__init__.py
GQCC/Methods/EntanglementStudy.py
GQCC/Methods/ExpectationValueSearch.py
GQCC/Methods/MultiplierScan.py
GQCC/Methods/PotentialEnergySurface.py
GQCC/Methods/__init__.py
GQCC/Optimization/SpinResolvedOptimizationFunctions.py
GQCC/Optimization/SpinResolvedOptimizer.py
GQCC/Optimization/SpinUnresolvedOptimizationFunctions.py
GQCC/Optimization/SpinUnresolvedOptimizer.py
GQCC/Optimization/__init__.py
GQCC/SpinResolvedConstraints/FCI.py
GQCC/SpinResolvedConstraints/HubbardFCI.py
GQCC/SpinResolvedConstraints/UHF.py
GQCC/SpinResolvedConstraints/UNOCI.py
GQCC/SpinResolvedConstraints/__init__.py
GQCC/SpinUnresolvedConstraints/FCI.py
GQCC/SpinUnresolvedConstraints/GHF.py
GQCC/SpinUnresolvedConstraints/GNOCI.py
GQCC/SpinUnresolvedConstraints/HubbardFCI.py
GQCC/SpinUnresolvedConstraints/UHF.py
GQCC/SpinUnresolvedConstraints/__init__.py
GQCConstraints-1.1.1.dist-info/LICENSE
GQCConstraints-1.1.1.dist-info/METADATA
GQCConstraints-1.1.1.dist-info/WHEEL
GQCConstraints-1.1.1.dist-info/top_level.txt
GQCConstraints-1.1.1.dist-info/RECORD
