Metadata-Version: 2.1
Name: GQCConstraints
Version: 1.1.1
Summary: This library build on GQCP provides easy to work with utilities in order to perform constrained quantum chemical calculations.
Author: The Ghent Quantum Chemistry Group
Keywords: quantum chemistry,constraints,GQCP
License-File: LICENSE
Requires-Dist: pandas ==1.2.5
Requires-Dist: numpy ==1.22.4
Requires-Dist: scipy ==1.7.0
